syd/__init__.py
syd/parameters.py
syd/support.py
syd/viewer.py
syd/flask_deployment/__init__.py
syd/flask_deployment/deployer.py
syd/flask_deployment/testing_principles.md
syd/flask_deployment/static/__init__.py
syd/flask_deployment/static/css/styles.css
syd/flask_deployment/static/css/viewer.css
syd/flask_deployment/static/js/old_viewer.js
syd/flask_deployment/static/js/viewer.js
syd/flask_deployment/static/js/modules/api.js
syd/flask_deployment/static/js/modules/config.js
syd/flask_deployment/static/js/modules/plot.js
syd/flask_deployment/static/js/modules/state.js
syd/flask_deployment/static/js/modules/system_controls.js
syd/flask_deployment/static/js/modules/ui_controls.js
syd/flask_deployment/static/js/modules/utils.js
syd/flask_deployment/templates/__init__.py
syd/flask_deployment/templates/index.html
syd/notebook_deployment/__init__.py
syd/notebook_deployment/deployer.py
syd/notebook_deployment/widgets.py
syd-1.2.6.dist-info/METADATA
syd-1.2.6.dist-info/WHEEL
syd-1.2.6.dist-info/licenses/LICENSE
syd-1.2.6.dist-info/RECORD
