Metadata-Version: 2.4
Name: syd
Version: 1.2.6
Summary: A Python package for making GUIs for data science easy.
Project-URL: Homepage, https://github.com/landoskape/syd
Author-email: Andrew Landau <andrew+tyler+landau+getridofthisanddtheplusses@gmail.com>
License-Expression: GPL-3.0-or-later
License-File: LICENSE
Keywords: data-science,gui,interactive,jupyter,machine-learning,notebook,python
Classifier: Development Status :: 4 - Beta
Classifier: Intended Audience :: Developers
Classifier: Intended Audience :: Science/Research
Classifier: License :: OSI Approved :: GNU General Public License v3 or later (GPLv3+)
Classifier: Operating System :: OS Independent
Classifier: Programming Language :: Python :: 3.8
Classifier: Programming Language :: Python :: 3.9
Classifier: Programming Language :: Python :: 3.10
Classifier: Programming Language :: Python :: 3.11
Classifier: Programming Language :: Python :: 3.12
Classifier: Programming Language :: Python :: 3.13
Requires-Python: >=3.8
Requires-Dist: flask
Requires-Dist: ipykernel
Requires-Dist: ipympl
Requires-Dist: ipywidgets
Requires-Dist: matplotlib
Provides-Extra: test
Requires-Dist: pytest-cov>=4.0.0; extra == 'test'
Requires-Dist: pytest>=7.0.0; extra == 'test'
